setup.py
CsuOpenpose.egg-info/PKG-INFO
CsuOpenpose.egg-info/SOURCES.txt
CsuOpenpose.egg-info/dependency_links.txt
CsuOpenpose.egg-info/requires.txt
CsuOpenpose.egg-info/top_level.txt
Openpose/__init__.py
Openpose/model.py
Openpose/src/__init__.py
Openpose/src/body.py
Openpose/src/hand.py
Openpose/src/hand_model_outputsize.py
Openpose/src/model.py
Openpose/src/util.py