Metadata-Version: 1.0
Name: CsuOpenpose
Version: 1.0.13
Summary: pose
Home-page: UNKNOWN
Author: csu_ywj
Author-email: UNKNOWN
License: MIT Licence
Keywords: pip,openpose
Platform: any
